dl2sparql/__init__.py
dl2sparql/_utils.py
dl2sparql/core.py
dl2sparql/io.py
dl2sparql/namespaces.py
dl2sparql/parser.py
dl2sparql/render.py
dl2sparql/util.py
dl2sparql/vocab.py
dl2sparql/ext/__init__.py
dl2sparql/model/__init__.py
dl2sparql/model/_base.py
dl2sparql/model/_iri.py
dl2sparql/model/providers.py
dl2sparql/owl2sparql/__init__.py
dl2sparql/owl2sparql/converter.py
dl2sparql/owlready2/__init__.py
dl2sparql/owlready2/_base.py
dl2sparql/owlready2/axioms.py
dl2sparql/owlready2/complex_ce_instances.py
dl2sparql/owlready2/plus.py
dl2sparql/owlready2/utils.py
tests/__init__.py
tests/test_owlapy.py
tests/test_owlapy_cnf_dnf.py
tests/test_owlapy_nnf.py
tests/test_owlapy_owl2sparql_converter.py
tests/test_owlapy_parser.py
tests/test_owlapy_render.py
dl2sparql-0.0.1.dist-info/METADATA
dl2sparql-0.0.1.dist-info/WHEEL
dl2sparql-0.0.1.dist-info/top_level.txt
dl2sparql-0.0.1.dist-info/RECORD
