Metadata-Version: 2.1
Name: dl2sparql
Version: 0.0.1
Summary: Description Logic Concept to SPARQL query
Home-page: https://github.com/dice-group/DL2SPARQL
Author: Caglar Demir
Author-email: caglardemir8@gmail.com
Classifier: Programming Language :: Python :: 3.9
Classifier: License :: OSI Approved :: MIT License
Requires-Python: >=3.9.18
Requires-Dist: pytest
Requires-Dist: pandas
Requires-Dist: parsimonious
Requires-Dist: rdflib
